[{
        "type": "床品",
        "id": 1,
        "list": [{
                "num": 1,
                "img": "1.jpg",
                "title": "欧式天丝四件套",
                "infor": "柔滑天丝，保护你的肌肤",
                "deta": "安静的你就 刷机大师啊手机电脑啊手机电脑及啊手机电脑案件圣诞节家十多年家家十多年家驾驶等不及啊氨基酸不的吉安市的 氨基酸的你加快速度卡机是按实际的煎熬开始到静安寺阿刷卡机的那棵就是你的可接受的节哀顺变道具卡金山毒霸卡萨丁吧世界加上你端午节你教我煎熬森度吉安开始打开就别拿金山毒霸啊就是你的静安寺南大街啊就是你的静安寺难度比",
                "price": "100"

            },
            {
                "num": 2,
                "img": "1.jpg",
                "title": "欧式天丝四件套",
                "infor": "柔滑天丝，保护你的肌肤",
                "deta": "安静的你就 刷机大师啊手机电脑啊手机电脑及啊手机电脑案件圣诞节家十多年家家十多年家驾驶等不及啊氨基酸不的吉安市的 氨基酸的你加快速度卡机是按实际的煎熬开始到静安寺阿刷卡机的那棵就是你的可接受的节哀顺变道具卡金山毒霸卡萨丁吧世界加上你端午节你教我煎熬森度吉安开始打开就别拿金山毒霸啊就是你的静安寺南大街啊就是你的静安寺难度比",
                "price": "100"
            }, {
                "num": 3,
                "img": "1.jpg",
                "title": "欧式天丝四件套",
                "infor": "柔滑天丝，保护你的肌肤",
                "deta": "安静的你就 刷机大师啊手机电脑啊手机电脑及啊手机电脑案件圣诞节家十多年家家十多年家驾驶等不及啊氨基酸不的吉安市的 氨基酸的你加快速度卡机是按实际的煎熬开始到静安寺阿刷卡机的那棵就是你的可接受的节哀顺变道具卡金山毒霸卡萨丁吧世界加上你端午节你教我煎熬森度吉安开始打开就别拿金山毒霸啊就是你的静安寺南大街啊就是你的静安寺难度比",
                "price": "100"
            }, {
                "num": 4,
                "img": "1.jpg",
                "title": "欧式天丝四件套",
                "infor": "柔滑天丝，保护你的肌肤",
                "deta": "安静的你就 刷机大师啊手机电脑啊手机电脑及啊手机电脑案件圣诞节家十多年家家十多年家驾驶等不及啊氨基酸不的吉安市的 氨基酸的你加快速度卡机是按实际的煎熬开始到静安寺阿刷卡机的那棵就是你的可接受的节哀顺变道具卡金山毒霸卡萨丁吧世界加上你端午节你教我煎熬森度吉安开始打开就别拿金山毒霸啊就是你的静安寺南大街啊就是你的静安寺难度比",
                "price": "100"
            }
        ]
    },
    {
        "type": "被套",
        "id": 2,
        "list": [{
                "num": 5,
                "img": "2.jpg",
                "title": "欧式天丝四件套",
                "infor": "柔滑天丝，保护你的肌肤",
                "deta": "安静的你就 刷机大师啊手机电脑啊手机电脑及啊手机电脑案件圣诞节家十多年家家十多年家驾驶等不及啊氨基酸不的吉安市的 氨基酸的你加快速度卡机是按实际的煎熬开始到静安寺阿刷卡机的那棵就是你的可接受的节哀顺变道具卡金山毒霸卡萨丁吧世界加上你端午节你教我煎熬森度吉安开始打开就别拿金山毒霸啊就是你的静安寺南大街啊就是你的静安寺难度比",
                "price": "100"
            },
            {
                "num": 6,
                "img": "2.jpg",
                "title": "欧式天丝四件套",
                "infor": "柔滑天丝，保护你的肌肤",
                "deta": "安静的你就 刷机大师啊手机电脑啊手机电脑及啊手机电脑案件圣诞节家十多年家家十多年家驾驶等不及啊氨基酸不的吉安市的 氨基酸的你加快速度卡机是按实际的煎熬开始到静安寺阿刷卡机的那棵就是你的可接受的节哀顺变道具卡金山毒霸卡萨丁吧世界加上你端午节你教我煎熬森度吉安开始打开就别拿金山毒霸啊就是你的静安寺南大街啊就是你的静安寺难度比",
                "price": "100"
            }, {
                "num": 7,
                "img": "2.jpg",
                "title": "欧式天丝四件套",
                "infor": "柔滑天丝，保护你的肌肤",
                "deta": "安静的你就 刷机大师啊手机电脑啊手机电脑及啊手机电脑案件圣诞节家十多年家家十多年家驾驶等不及啊氨基酸不的吉安市的 氨基酸的你加快速度卡机是按实际的煎熬开始到静安寺阿刷卡机的那棵就是你的可接受的节哀顺变道具卡金山毒霸卡萨丁吧世界加上你端午节你教我煎熬森度吉安开始打开就别拿金山毒霸啊就是你的静安寺南大街啊就是你的静安寺难度比",
                "price": "100"
            }, {
                "num": 8,
                "img": "2.jpg",
                "title": "欧式天丝四件套",
                "infor": "柔滑天丝，保护你的肌肤",
                "deta": "安静的你就 刷机大师啊手机电脑啊手机电脑及啊手机电脑案件圣诞节家十多年家家十多年家驾驶等不及啊氨基酸不的吉安市的 氨基酸的你加快速度卡机是按实际的煎熬开始到静安寺阿刷卡机的那棵就是你的可接受的节哀顺变道具卡金山毒霸卡萨丁吧世界加上你端午节你教我煎熬森度吉安开始打开就别拿金山毒霸啊就是你的静安寺南大街啊就是你的静安寺难度比",
                "price": "100"
            }
        ]
    }, {
        "type": "抱枕",
        "id": 3,
        "list": [{
                "num": 9,
                "img": "3.jpg",
                "title": "欧式天丝四件套",
                "infor": "柔滑天丝，保护你的肌肤",
                "deta": "安静的你就 刷机大师啊手机电脑啊手机电脑及啊手机电脑案件圣诞节家十多年家家十多年家驾驶等不及啊氨基酸不的吉安市的 氨基酸的你加快速度卡机是按实际的煎熬开始到静安寺阿刷卡机的那棵就是你的可接受的节哀顺变道具卡金山毒霸卡萨丁吧世界加上你端午节你教我煎熬森度吉安开始打开就别拿金山毒霸啊就是你的静安寺南大街啊就是你的静安寺难度比",
                "price": "100"
            },
            {
                "num": 10,
                "img": "3.jpg",
                "title": "欧式天丝四件套",
                "infor": "柔滑天丝，保护你的肌肤",
                "deta": "安静的你就 刷机大师啊手机电脑啊手机电脑及啊手机电脑案件圣诞节家十多年家家十多年家驾驶等不及啊氨基酸不的吉安市的 氨基酸的你加快速度卡机是按实际的煎熬开始到静安寺阿刷卡机的那棵就是你的可接受的节哀顺变道具卡金山毒霸卡萨丁吧世界加上你端午节你教我煎熬森度吉安开始打开就别拿金山毒霸啊就是你的静安寺南大街啊就是你的静安寺难度比",
                "price": "100"
            }, {
                "num": 11,
                "img": "3.jpg",
                "title": "欧式天丝四件套",
                "infor": "柔滑天丝，保护你的肌肤",
                "deta": "安静的你就 刷机大师啊手机电脑啊手机电脑及啊手机电脑案件圣诞节家十多年家家十多年家驾驶等不及啊氨基酸不的吉安市的 氨基酸的你加快速度卡机是按实际的煎熬开始到静安寺阿刷卡机的那棵就是你的可接受的节哀顺变道具卡金山毒霸卡萨丁吧世界加上你端午节你教我煎熬森度吉安开始打开就别拿金山毒霸啊就是你的静安寺南大街啊就是你的静安寺难度比",
                "price": "100"
            }, {
                "num": 12,
                "img": "3.jpg",
                "title": "欧式天丝四件套",
                "infor": "柔滑天丝，保护你的肌肤",
                "deta": "安静的你就 刷机大师啊手机电脑啊手机电脑及啊手机电脑案件圣诞节家十多年家家十多年家驾驶等不及啊氨基酸不的吉安市的 氨基酸的你加快速度卡机是按实际的煎熬开始到静安寺阿刷卡机的那棵就是你的可接受的节哀顺变道具卡金山毒霸卡萨丁吧世界加上你端午节你教我煎熬森度吉安开始打开就别拿金山毒霸啊就是你的静安寺南大街啊就是你的静安寺难度比",
                "price": "100"
            }
        ]
    },
    {
        "type": "家居",
        "id": 4,
        "list": [{
                "num": 13,
                "img": "4.jpg",
                "title": "欧式天丝四件套",
                "infor": "柔滑天丝，保护你的肌肤",
                "deta": "安静的你就 刷机大师啊手机电脑啊手机电脑及啊手机电脑案件圣诞节家十多年家家十多年家驾驶等不及啊氨基酸不的吉安市的 氨基酸的你加快速度卡机是按实际的煎熬开始到静安寺阿刷卡机的那棵就是你的可接受的节哀顺变道具卡金山毒霸卡萨丁吧世界加上你端午节你教我煎熬森度吉安开始打开就别拿金山毒霸啊就是你的静安寺南大街啊就是你的静安寺难度比",
                "price": "100"
            },
            {
                "num": 14,
                "img": "4.jpg",
                "title": "欧式天丝四件套",
                "infor": "柔滑天丝，保护你的肌肤",
                "deta": "安静的你就 刷机大师啊手机电脑啊手机电脑及啊手机电脑案件圣诞节家十多年家家十多年家驾驶等不及啊氨基酸不的吉安市的 氨基酸的你加快速度卡机是按实际的煎熬开始到静安寺阿刷卡机的那棵就是你的可接受的节哀顺变道具卡金山毒霸卡萨丁吧世界加上你端午节你教我煎熬森度吉安开始打开就别拿金山毒霸啊就是你的静安寺南大街啊就是你的静安寺难度比",
                "price": "100"
            }, {
                "num": 15,
                "img": "4.jpg",
                "title": "欧式天丝四件套",
                "infor": "柔滑天丝，保护你的肌肤",
                "deta": "安静的你就 刷机大师啊手机电脑啊手机电脑及啊手机电脑案件圣诞节家十多年家家十多年家驾驶等不及啊氨基酸不的吉安市的 氨基酸的你加快速度卡机是按实际的煎熬开始到静安寺阿刷卡机的那棵就是你的可接受的节哀顺变道具卡金山毒霸卡萨丁吧世界加上你端午节你教我煎熬森度吉安开始打开就别拿金山毒霸啊就是你的静安寺南大街啊就是你的静安寺难度比",
                "price": "100"
            }, {
                "num": 16,
                "img": "4.jpg",
                "title": "欧式天丝四件套",
                "infor": "柔滑天丝，保护你的肌肤",
                "deta": "安静的你就 刷机大师啊手机电脑啊手机电脑及啊手机电脑案件圣诞节家十多年家家十多年家驾驶等不及啊氨基酸不的吉安市的 氨基酸的你加快速度卡机是按实际的煎熬开始到静安寺阿刷卡机的那棵就是你的可接受的节哀顺变道具卡金山毒霸卡萨丁吧世界加上你端午节你教我煎熬森度吉安开始打开就别拿金山毒霸啊就是你的静安寺南大街啊就是你的静安寺难度比",
                "price": "100"
            }
        ]
    },
    {
        "type": "收纳",
        "id": 5,
        "list": [{
                "num": 17,
                "img": "4.jpg",
                "title": "欧式天丝四件套",
                "infor": "柔滑天丝，保护你的肌肤",
                "deta": "安静的你就 刷机大师啊手机电脑啊手机电脑及啊手机电脑案件圣诞节家十多年家家十多年家驾驶等不及啊氨基酸不的吉安市的 氨基酸的你加快速度卡机是按实际的煎熬开始到静安寺阿刷卡机的那棵就是你的可接受的节哀顺变道具卡金山毒霸卡萨丁吧世界加上你端午节你教我煎熬森度吉安开始打开就别拿金山毒霸啊就是你的静安寺南大街啊就是你的静安寺难度比",
                "price": "100"
            },
            {
                "num": 18,
                "img": "4.jpg",
                "title": "欧式天丝四件套",
                "infor": "柔滑天丝，保护你的肌肤",
                "deta": "安静的你就 刷机大师啊手机电脑啊手机电脑及啊手机电脑案件圣诞节家十多年家家十多年家驾驶等不及啊氨基酸不的吉安市的 氨基酸的你加快速度卡机是按实际的煎熬开始到静安寺阿刷卡机的那棵就是你的可接受的节哀顺变道具卡金山毒霸卡萨丁吧世界加上你端午节你教我煎熬森度吉安开始打开就别拿金山毒霸啊就是你的静安寺南大街啊就是你的静安寺难度比",
                "price": "100"
            }, {
                "num": 19,
                "img": "4.jpg",
                "title": "欧式天丝四件套",
                "infor": "柔滑天丝，保护你的肌肤",
                "deta": "安静的你就 刷机大师啊手机电脑啊手机电脑及啊手机电脑案件圣诞节家十多年家家十多年家驾驶等不及啊氨基酸不的吉安市的 氨基酸的你加快速度卡机是按实际的煎熬开始到静安寺阿刷卡机的那棵就是你的可接受的节哀顺变道具卡金山毒霸卡萨丁吧世界加上你端午节你教我煎熬森度吉安开始打开就别拿金山毒霸啊就是你的静安寺南大街啊就是你的静安寺难度比",
                "price": "100"
            }, {
                "num": 20,
                "img": "4.jpg",
                "title": "欧式天丝四件套",
                "infor": "柔滑天丝，保护你的肌肤",
                "deta": "安静的你就 刷机大师啊手机电脑啊手机电脑及啊手机电脑案件圣诞节家十多年家家十多年家驾驶等不及啊氨基酸不的吉安市的 氨基酸的你加快速度卡机是按实际的煎熬开始到静安寺阿刷卡机的那棵就是你的可接受的节哀顺变道具卡金山毒霸卡萨丁吧世界加上你端午节你教我煎熬森度吉安开始打开就别拿金山毒霸啊就是你的静安寺南大街啊就是你的静安寺难度比",
                "price": "100"
            }
        ]
    },
    {
        "type": "布艺",
        "id": 6,
        "list": [{
                "num": 21,
                "img": "4.jpg",
                "title": "欧式天丝四件套",
                "infor": "柔滑天丝，保护你的肌肤",
                "deta": "安静的你就 刷机大师啊手机电脑啊手机电脑及啊手机电脑案件圣诞节家十多年家家十多年家驾驶等不及啊氨基酸不的吉安市的 氨基酸的你加快速度卡机是按实际的煎熬开始到静安寺阿刷卡机的那棵就是你的可接受的节哀顺变道具卡金山毒霸卡萨丁吧世界加上你端午节你教我煎熬森度吉安开始打开就别拿金山毒霸啊就是你的静安寺南大街啊就是你的静安寺难度比",
                "price": "100"
            },
            {
                "num": 22,
                "img": "4.jpg",
                "title": "欧式天丝四件套",
                "infor": "柔滑天丝，保护你的肌肤",
                "deta": "安静的你就 刷机大师啊手机电脑啊手机电脑及啊手机电脑案件圣诞节家十多年家家十多年家驾驶等不及啊氨基酸不的吉安市的 氨基酸的你加快速度卡机是按实际的煎熬开始到静安寺阿刷卡机的那棵就是你的可接受的节哀顺变道具卡金山毒霸卡萨丁吧世界加上你端午节你教我煎熬森度吉安开始打开就别拿金山毒霸啊就是你的静安寺南大街啊就是你的静安寺难度比",
                "price": "100"
            }, {
                "num": 23,
                "img": "4.jpg",
                "title": "欧式天丝四件套",
                "infor": "柔滑天丝，保护你的肌肤",
                "deta": "安静的你就 刷机大师啊手机电脑啊手机电脑及啊手机电脑案件圣诞节家十多年家家十多年家驾驶等不及啊氨基酸不的吉安市的 氨基酸的你加快速度卡机是按实际的煎熬开始到静安寺阿刷卡机的那棵就是你的可接受的节哀顺变道具卡金山毒霸卡萨丁吧世界加上你端午节你教我煎熬森度吉安开始打开就别拿金山毒霸啊就是你的静安寺南大街啊就是你的静安寺难度比",
                "price": "100"
            }, {
                "num": 24,
                "img": "4.jpg",
                "title": "欧式天丝四件套",
                "infor": "柔滑天丝，保护你的肌肤",
                "deta": "安静的你就 刷机大师啊手机电脑啊手机电脑及啊手机电脑案件圣诞节家十多年家家十多年家驾驶等不及啊氨基酸不的吉安市的 氨基酸的你加快速度卡机是按实际的煎熬开始到静安寺阿刷卡机的那棵就是你的可接受的节哀顺变道具卡金山毒霸卡萨丁吧世界加上你端午节你教我煎熬森度吉安开始打开就别拿金山毒霸啊就是你的静安寺南大街啊就是你的静安寺难度比",
                "price": "100"
            }
        ]
    },
    {
        "type": "软装",
        "id": 7,
        "list": [{
                "num": 25,
                "img": "4.jpg",
                "title": "欧式天丝四件套",
                "infor": "柔滑天丝，保护你的肌肤",
                "deta": "安静的你就 刷机大师啊手机电脑啊手机电脑及啊手机电脑案件圣诞节家十多年家家十多年家驾驶等不及啊氨基酸不的吉安市的 氨基酸的你加快速度卡机是按实际的煎熬开始到静安寺阿刷卡机的那棵就是你的可接受的节哀顺变道具卡金山毒霸卡萨丁吧世界加上你端午节你教我煎熬森度吉安开始打开就别拿金山毒霸啊就是你的静安寺南大街啊就是你的静安寺难度比",
                "price": "100"
            },
            {
                "num": 26,
                "img": "4.jpg",
                "title": "欧式天丝四件套",
                "infor": "柔滑天丝，保护你的肌肤",
                "deta": "安静的你就 刷机大师啊手机电脑啊手机电脑及啊手机电脑案件圣诞节家十多年家家十多年家驾驶等不及啊氨基酸不的吉安市的 氨基酸的你加快速度卡机是按实际的煎熬开始到静安寺阿刷卡机的那棵就是你的可接受的节哀顺变道具卡金山毒霸卡萨丁吧世界加上你端午节你教我煎熬森度吉安开始打开就别拿金山毒霸啊就是你的静安寺南大街啊就是你的静安寺难度比",
                "price": "100"
            }, {
                "num": 27,
                "img": "4.jpg",
                "title": "欧式天丝四件套",
                "infor": "柔滑天丝，保护你的肌肤",
                "deta": "安静的你就 刷机大师啊手机电脑啊手机电脑及啊手机电脑案件圣诞节家十多年家家十多年家驾驶等不及啊氨基酸不的吉安市的 氨基酸的你加快速度卡机是按实际的煎熬开始到静安寺阿刷卡机的那棵就是你的可接受的节哀顺变道具卡金山毒霸卡萨丁吧世界加上你端午节你教我煎熬森度吉安开始打开就别拿金山毒霸啊就是你的静安寺南大街啊就是你的静安寺难度比",
                "price": "100"
            }, {
                "num": 28,
                "img": "4.jpg",
                "title": "欧式天丝四件套",
                "infor": "柔滑天丝，保护你的肌肤",
                "deta": "安静的你就 刷机大师啊手机电脑啊手机电脑及啊手机电脑案件圣诞节家十多年家家十多年家驾驶等不及啊氨基酸不的吉安市的 氨基酸的你加快速度卡机是按实际的煎熬开始到静安寺阿刷卡机的那棵就是你的可接受的节哀顺变道具卡金山毒霸卡萨丁吧世界加上你端午节你教我煎熬森度吉安开始打开就别拿金山毒霸啊就是你的静安寺南大街啊就是你的静安寺难度比",
                "price": "100"
            }
        ]
    }
]